{
  "name": "improvement-1771978250-7",
  "description": "Create API rate limiting and authentication tokens",
  "status": "completed",
  "priority": "normal",
  "created": "2026-02-25T01:10:50+01:00",
  "assignee": "self",
  "subtasks": [],
  "completed": true,
  "completed_at": "2026-02-25T09:42:00+01:00",
  "attempts": 1,
  "max_attempts": 3,
  "verification": "Created lib/api-auth.sh with token generation, validation, rate limiting (100/hour default), scopes, and revocation. Added 'autonomy api-auth' command. Tested: generated token 'web-ui', validated successfully, list shows token details",
  "evidence": [
    "lib/api-auth.sh exists and is executable",
    "state/api-tokens.json contains test token",
    "Token validation returns valid=true with remaining count",
    "autonomy api-auth list shows token details"
  ],
  "source": "auto_generated",
  "flagged_at": "2026-02-25T09:32:16+01:00",
  "flagged_by": "daemon",
  "processing_started": "2026-02-25T09:37:00+01:00"
}
